jsonifyer/__init__.py
jsonifyer/api.py
jsonifyer/config.py
jsonifyer/config_loader.py
jsonifyer/main.py
jsonifyer/converter/__init__.py
jsonifyer/converter/csv_converter.py
jsonifyer/converter/python_converter.py
jsonifyer/converter/xslt_converter.py
jsonifyer-0.1.10.dist-info/licenses/LICENSE
jsonifyer-0.1.10.dist-info/METADATA
jsonifyer-0.1.10.dist-info/WHEEL
jsonifyer-0.1.10.dist-info/entry_points.txt
jsonifyer-0.1.10.dist-info/top_level.txt
jsonifyer-0.1.10.dist-info/RECORD
