Metadata-Version: 2.4
Name: jsonifyer
Version: 0.1.10
Summary: Convert files to JSON format
Home-page: https://github.com/yourusername/jsonify
Author: Carol
Author-email: Carolina Pereira <carolinadpereira18@gmail.com>, Matilde Pato <matilde.pato@isel.pt>
Maintainer-email: Carolina Pereira <carolinadpereira18@gmail.com>, Matilde Pato <matilde.pato@isel.pt>
License: MIT
Project-URL: Homepage, https://github.com/crpereir/jsonify
Project-URL: Issues, https://github.com/crpereir/jsonify/issues
Project-URL: Repository, https://github.com/crpereir/jsonify.git
Classifier: Programming Language :: Python :: 3
Classifier: Programming Language :: Python :: 3.7
Classifier: Programming Language :: Python :: 3.8
Classifier: Programming Language :: Python :: 3.9
Classifier: Programming Language :: Python :: 3.10
Classifier: Programming Language :: Python :: 3.11
Classifier: License :: OSI Approved :: MIT License
Classifier: Operating System :: OS Independent
Classifier: Development Status :: 4 - Beta
Classifier: Intended Audience :: Developers
Classifier: Topic :: Software Development :: Libraries :: Python Modules
Classifier: Topic :: Text Processing :: General
Requires-Python: >=3.8
License-File: LICENSE
Requires-Dist: beautifulsoup4
Requires-Dist: tqdm==4.67.1
Requires-Dist: lxml
Requires-Dist: pandas
Requires-Dist: openpyxl
Requires-Dist: pytest
Dynamic: author
Dynamic: home-page
Dynamic: license-file
Dynamic: requires-python
